webpy/__init__.py
webpy/__main__.py
webpy/fs_routes.py
webpy/pysite_semantic_tags.py
webpy/pyx_snippets.py
webpy_framework-3.0.0.dist-info/licenses/LICENSE
webpy_framework-3.0.0.dist-info/METADATA
webpy_framework-3.0.0.dist-info/WHEEL
webpy_framework-3.0.0.dist-info/entry_points.txt
webpy_framework-3.0.0.dist-info/top_level.txt
webpy_framework-3.0.0.dist-info/RECORD
