Metadata-Version: 2.4
Name: webpy-framework
Version: 3.0.0
Summary: Easy-to-use Python web framework built on top of Flask
Author-email: Carl Furtado <carlzfurtado@gmail.com>
License: MIT License
Project-URL: Homepage, https://github.com/User0332/webpy
Project-URL: Documentation, https://webpy-framework.readthedocs.io/
Keywords: framework,flask,web,server,html,markdown,pyx,wsgi,http,xml,asgi,deployment,uvicorn
Classifier: License :: OSI Approved :: MIT License
Classifier: Programming Language :: Python
Classifier: Programming Language :: Python :: 3
Classifier: Topic :: Text Processing :: Markup :: HTML
Classifier: Operating System :: OS Independent
Classifier: Topic :: Text Processing :: Markup :: Markdown
Classifier: Topic :: Text Processing :: Markup :: XML
Classifier: Framework :: Flask
Classifier: Topic :: Internet :: WWW/HTTP :: HTTP Servers
Classifier: Topic :: Internet :: WWW/HTTP :: WSGI :: Server
Classifier: Intended Audience :: Developers
Classifier: Intended Audience :: Information Technology
Classifier: Topic :: Text Processing :: Markup
Classifier: Topic :: Software Development :: Build Tools
Requires-Python: >=3.9
License-File: LICENSE
Requires-Dist: flask>=2.3.2
Requires-Dist: dill>=0.3.6
Requires-Dist: python-minifier>=2.9.0
Requires-Dist: dill>=0.3.6
Requires-Dist: flask-session>=0.5.0
Requires-Dist: flask-sqlalchemy>=3.0.3
Requires-Dist: pyx-pysite>=1.0.3
Requires-Dist: marko>=1.3.0
Requires-Dist: waitress>=2.1.2
Requires-Dist: asgiref>=3.7.2
Requires-Dist: uvicorn>=0.22.0
Dynamic: license-file
